{
	"mapwidth": "600",
	"mapheight": "900",
	"categories": [
		{ 
			 
		}
	], 
	"levels": [
		{
			"id": "free-view",
			"title": "Free Roam",
			"map":"maps/routing/cvm-cbm-m.jpg",
			"locations": [
				{
					"id": "r-cbm-m",
					"title": "College of Business Management",
                    "about": "",
                    "description": "",
                    "link": "#/app/pr-cbm-m",
                    "image": "img/cmu/BuildingPreviews/colleges/cbm-m.jpg",
                     "pin": "red iconpin fa ion-android-walk",
                    "x": "0.5767",
                    "y": "0.2107"
				}, 
				{			
					"id": "r-cvm-m",
					"title": "College of Veterinary Medicine",
                    "about": "",
                    "description": "",
                    "link": "#/app/pr-cvm-m",
                    "image": "img/cmu/BuildingPreviews/colleges/cvm-m.jpg",
                     "pin": "red iconpin fa ion-android-walk",
                    "x": "0.5250",
                    "y": "0.1216"
				}
			]
		}	
	]
}